rng_to_form/__init__.py
rng_to_form/form_maker.py
rng_to_form/rng.py
rng_to_html_form-1.0.2.dist-info/DESCRIPTION.rst
rng_to_html_form-1.0.2.dist-info/METADATA
rng_to_html_form-1.0.2.dist-info/RECORD
rng_to_html_form-1.0.2.dist-info/WHEEL
rng_to_html_form-1.0.2.dist-info/metadata.json
rng_to_html_form-1.0.2.dist-info/top_level.txt
tests/__init__.py
tests/test_form_maker.py
tests/test_rng.py
