Metadata-Version: 2.0
Name: rng-to-html-form
Version: 1.0.2
Summary: Takes an rng file and makes an html form
Home-page: https://github.com/unistra/rng-to-html-form
Author: di-dip-unistra
Author-email: di-dip@unistra.fr
License: PSF
Download-URL: http://pypi.python.org/pypi/rng-to-html-form
Keywords: lxml,python,rng,xml,form,html
Platform: UNKNOWN
Classifier: Development Status :: 4 - Beta
Classifier: Intended Audience :: Developers
Classifier: License :: OSI Approved :: Python Software Foundation License
Classifier: Operating System :: OS Independent
Classifier: Programming Language :: Python :: 3.4
Requires-Dist: lxml (==3.4.4)
